hdsemg_pipe/__init__.py
hdsemg_pipe/main.py
hdsemg_pipe/make_version.py
hdsemg_pipe/resources_rc.py
hdsemg_pipe/version.py
hdsemg_pipe/_log/__init__.py
hdsemg_pipe/_log/exception_hook.py
hdsemg_pipe/_log/log_config.py
hdsemg_pipe/actions/__init__.py
hdsemg_pipe/actions/crop_roi.py
hdsemg_pipe/actions/file_manager.py
hdsemg_pipe/actions/file_utils.py
hdsemg_pipe/actions/grid_associations.py
hdsemg_pipe/actions/json_file_utilities.py
hdsemg_pipe/actions/openfile.py
hdsemg_pipe/actions/workers.py
hdsemg_pipe/actions/enum/FolderNames.py
hdsemg_pipe/actions/enum/__init__.py
hdsemg_pipe/config/__init__.py
hdsemg_pipe/config/config_enums.py
hdsemg_pipe/config/config_manager.py
hdsemg_pipe/controller/__init__.py
hdsemg_pipe/controller/automatic_state_reconstruction.py
hdsemg_pipe/settings/__init__.py
hdsemg_pipe/settings/settings_dialog.py
hdsemg_pipe/settings/tabs/__init__.py
hdsemg_pipe/settings/tabs/channelselection.py
hdsemg_pipe/settings/tabs/installer.py
hdsemg_pipe/settings/tabs/log_setting.py
hdsemg_pipe/settings/tabs/openhdemg.py
hdsemg_pipe/settings/tabs/workfolder.py
hdsemg_pipe/state/__init__.py
hdsemg_pipe/state/global_state.py
hdsemg_pipe/ui_elements/__init__.py
hdsemg_pipe/ui_elements/loadingbutton.py
hdsemg_pipe/widgets/BaseStepWidget.py
hdsemg_pipe/widgets/ChannelSelectionStepWidget.py
hdsemg_pipe/widgets/DecompositionStepWidget.py
hdsemg_pipe/widgets/DefineRoiStepWidget.py
hdsemg_pipe/widgets/FolderContentWidget.py
hdsemg_pipe/widgets/GridAssociationStepWidget.py
hdsemg_pipe/widgets/MappingDialog.py
hdsemg_pipe/widgets/OpenFileStepWidget.py
hdsemg_pipe/widgets/__init__.py
hdsemg_pipe-0.11.1.dist-info/METADATA
hdsemg_pipe-0.11.1.dist-info/WHEEL
hdsemg_pipe-0.11.1.dist-info/entry_points.txt
hdsemg_pipe-0.11.1.dist-info/top_level.txt
hdsemg_pipe-0.11.1.dist-info/RECORD
