Metadata-Version: 2.4
Name: hdsemg-pipe
Version: 0.11.1
Summary: hdsemg-pipe package
Home-page: https://github.com/johanneskasser/hdsemg-pipe
Author: Johannes Kasser
Author-email: johanneskasser@outlook.de
Classifier: Programming Language :: Python :: 3
Classifier: License :: OSI Approved :: MIT License
Classifier: Operating System :: OS Independent
Requires-Python: >=3.7
Requires-Dist: PyQt5>=5.15.0
Requires-Dist: pyqt5-tools>=5.15.0; sys_platform == "win32"
Requires-Dist: matplotlib>=3.4.0
Requires-Dist: numpy>=1.21.0
Requires-Dist: scipy>=1.7.0
Requires-Dist: pyinstaller>=6.11.0
Requires-Dist: pandas>=1.3.5
Requires-Dist: torch>=1.10.0
Requires-Dist: requests>=2.26.0
Requires-Dist: hdsemg-shared>=0.10.7
Requires-Dist: hdsemg-select>=0.0.5
Requires-Dist: openhdemg>=0.1.2
Requires-Dist: pefile>=2023.2.7; sys_platform != "win32"
Dynamic: author
Dynamic: author-email
Dynamic: classifier
Dynamic: description
Dynamic: description-content-type
Dynamic: home-page
Dynamic: requires-dist
Dynamic: requires-python
Dynamic: summary
